flask_swagger_generator/__init__.py
flask_swagger_generator/exceptions.py
flask_swagger_generator/components/__init__.py
flask_swagger_generator/components/swagger_models.py
flask_swagger_generator/components/swagger_version.py
flask_swagger_generator/components/version_three/__init__.py
flask_swagger_generator/components/version_three/operation_id.py
flask_swagger_generator/components/version_three/parameters.py
flask_swagger_generator/components/version_three/path.py
flask_swagger_generator/components/version_three/path_parameter.py
flask_swagger_generator/components/version_three/query_parameter.py
flask_swagger_generator/components/version_three/request_body.py
flask_swagger_generator/components/version_three/request_type.py
flask_swagger_generator/components/version_three/response.py
flask_swagger_generator/components/version_three/responses.py
flask_swagger_generator/components/version_three/schema_attribute.py
flask_swagger_generator/components/version_three/schemas.py
flask_swagger_generator/components/version_three/security.py
flask_swagger_generator/components/version_three/tag.py
flask_swagger_generator/generators/__init__.py
flask_swagger_generator/generators/generator.py
flask_swagger_generator/generators/swagger_view.py
flask_swagger_generator/specifiers/__init__.py
flask_swagger_generator/specifiers/swagger_specifier.py
flask_swagger_generator/specifiers/version_three_specifier.py
flask_swagger_generator/utils/__init__.py
flask_swagger_generator/utils/input_type.py
flask_swagger_generator/utils/parameter_type.py
flask_swagger_generator/utils/property_type.py
flask_swagger_generator/utils/random.py
flask_swagger_generator/utils/request_type.py
flask_swagger_generator/utils/schema_type.py
flask_swagger_generator/utils/security_type.py
flask_swagger_generator/utils/swagger_version.py
flask_swagger_generator/utils/url_variable_type.py
flask_swagger_generator/utils/utils.py
flask_swagger_init-24.14.1.dist-info/AUTHORS.md
flask_swagger_init-24.14.1.dist-info/LICENSE
flask_swagger_init-24.14.1.dist-info/METADATA
flask_swagger_init-24.14.1.dist-info/WHEEL
flask_swagger_init-24.14.1.dist-info/top_level.txt
flask_swagger_init-24.14.1.dist-info/RECORD
