Metadata-Version: 2.1
Name: flask-swagger-init
Version: 24.14.1
Summary: A library for generating and publishing Swagger specifications for Flask applications.
Home-page: https://github.com/krlsedu/flask-swagger-generator.git
Author: Carlos Eduardo
License: MIT
Keywords: Flask,swagger,swagger generator,OpenAPI
Classifier: Intended Audience :: Developers
Classifier: Programming Language :: Python :: 3
Classifier: Programming Language :: Python :: 3.4
Classifier: Programming Language :: Python :: 3.5
Classifier: Programming Language :: Python :: 3.6
Classifier: Topic :: Software Development
Requires-Python: >=3
License-File: LICENSE
License-File: AUTHORS.md
Requires-Dist: flask ~=3.0.0
Requires-Dist: marshmallow >=3.0.0
Requires-Dist: setuptools >=65.5.1
Requires-Dist: flask-swagger-ui >=3.25.0
